Metadata-Version: 2.1
Name: fakertype
Version: 0.0.1a2
Summary: Generate fake data in specified type data
Home-page: https://github.com/yasirroni/fakertype
Author: Muhammad Yasirroni
Author-email: muhammadyasirroni@gmail.com
License: UNKNOWN
Platform: UNKNOWN
Classifier: Programming Language :: Python
Requires-Python: >=3.6
